MANIFEST.in
README.md
setup.py
lbdata_load_tools/__init__.py
lbdata_load_tools/helpers.py
lbdata_load_tools/presets.py
lbdata_load_tools.egg-info/PKG-INFO
lbdata_load_tools.egg-info/SOURCES.txt
lbdata_load_tools.egg-info/dependency_links.txt
lbdata_load_tools.egg-info/requires.txt
lbdata_load_tools.egg-info/top_level.txt