Metadata-Version: 1.0
Name: lbdata-load-tools
Version: 0.0.7
Summary: Tools to help loading data in Redshift
Home-page: https://github.com/lovebonito/lbdata_load_tools
Author: Alexandre PECCAUD
Author-email: alexandre.peccaud@gmail.com
License: UNKNOWN
Platform: UNKNOWN
